{
  "id": "8a4aefd4-e2cc-47b9-bd22-0107e5f1988b",
  "prevId": "00000000-0000-0000-0000-000000000000",
  "version": "7",
  "dialect": "postgresql",
  "tables": {
    "public.cohorts": {
      "name": "cohorts",
      "schema": "",
      "columns": {
        "id": {
          "name": "id",
          "type": "uuid",
          "primaryKey": true,
          "notNull": true,
          "default": "gen_random_uuid()"
        },
        "name": {
          "name": "name",
          "type": "text",
          "primaryKey": false,
          "notNull": true
        },
        "min_grade": {
          "name": "min_grade",
          "type": "integer",
          "primaryKey": false,
          "notNull": true
        },
        "max_grade": {
          "name": "max_grade",
          "type": "integer",
          "primaryKey": false,
          "notNull": true
        },
        "is_active": {
          "name": "is_active",
          "type": "boolean",
          "primaryKey": false,
          "notNull": true,
          "default": true
        },
        "created_at": {
          "name": "created_at",
          "type": "timestamp with time zone",
          "primaryKey": false,
          "notNull": true,
          "default": "now()"
        }
      },
      "indexes": {},
      "foreignKeys": {},
      "compositePrimaryKeys": {},
      "uniqueConstraints": {},
      "policies": {},
      "checkConstraints": {},
      "isRLSEnabled": false
    },
    "public.community_replies": {
      "name": "community_replies",
      "schema": "",
      "columns": {
        "id": {
          "name": "id",
          "type": "uuid",
          "primaryKey": true,
          "notNull": true,
          "default": "gen_random_uuid()"
        },
        "thread_id": {
          "name": "thread_id",
          "type": "uuid",
          "primaryKey": false,
          "notNull": true
        },
        "author_id": {
          "name": "author_id",
          "type": "uuid",
          "primaryKey": false,
          "notNull": true
        },
        "author_name": {
          "name": "author_name",
          "type": "text",
          "primaryKey": false,
          "notNull": true
        },
        "body": {
          "name": "body",
          "type": "text",
          "primaryKey": false,
          "notNull": true
        },
        "is_moderator_reply": {
          "name": "is_moderator_reply",
          "type": "boolean",
          "primaryKey": false,
          "notNull": true,
          "default": false
        },
        "is_hidden": {
          "name": "is_hidden",
          "type": "boolean",
          "primaryKey": false,
          "notNull": true,
          "default": false
        },
        "created_at": {
          "name": "created_at",
          "type": "timestamp with time zone",
          "primaryKey": false,
          "notNull": true,
          "default": "now()"
        }
      },
      "indexes": {},
      "foreignKeys": {
        "community_replies_thread_id_community_threads_id_fk": {
          "name": "community_replies_thread_id_community_threads_id_fk",
          "tableFrom": "community_replies",
          "tableTo": "community_threads",
          "columnsFrom": [
            "thread_id"
          ],
          "columnsTo": [
            "id"
          ],
          "onDelete": "no action",
          "onUpdate": "no action"
        }
      },
      "compositePrimaryKeys": {},
      "uniqueConstraints": {},
      "policies": {},
      "checkConstraints": {},
      "isRLSEnabled": false
    },
    "public.community_threads": {
      "name": "community_threads",
      "schema": "",
      "columns": {
        "id": {
          "name": "id",
          "type": "uuid",
          "primaryKey": true,
          "notNull": true,
          "default": "gen_random_uuid()"
        },
        "school_id": {
          "name": "school_id",
          "type": "uuid",
          "primaryKey": false,
          "notNull": true
        },
        "course_id": {
          "name": "course_id",
          "type": "uuid",
          "primaryKey": false,
          "notNull": false
        },
        "module_id": {
          "name": "module_id",
          "type": "uuid",
          "primaryKey": false,
          "notNull": false
        },
        "author_id": {
          "name": "author_id",
          "type": "uuid",
          "primaryKey": false,
          "notNull": true
        },
        "author_name": {
          "name": "author_name",
          "type": "text",
          "primaryKey": false,
          "notNull": true
        },
        "title": {
          "name": "title",
          "type": "text",
          "primaryKey": false,
          "notNull": true
        },
        "body": {
          "name": "body",
          "type": "text",
          "primaryKey": false,
          "notNull": true
        },
        "is_moderator_post": {
          "name": "is_moderator_post",
          "type": "boolean",
          "primaryKey": false,
          "notNull": true,
          "default": false
        },
        "is_pinned": {
          "name": "is_pinned",
          "type": "boolean",
          "primaryKey": false,
          "notNull": true,
          "default": false
        },
        "is_hidden": {
          "name": "is_hidden",
          "type": "boolean",
          "primaryKey": false,
          "notNull": true,
          "default": false
        },
        "created_at": {
          "name": "created_at",
          "type": "timestamp with time zone",
          "primaryKey": false,
          "notNull": true,
          "default": "now()"
        }
      },
      "indexes": {},
      "foreignKeys": {
        "community_threads_school_id_schools_id_fk": {
          "name": "community_threads_school_id_schools_id_fk",
          "tableFrom": "community_threads",
          "tableTo": "schools",
          "columnsFrom": [
            "school_id"
          ],
          "columnsTo": [
            "id"
          ],
          "onDelete": "no action",
          "onUpdate": "no action"
        },
        "community_threads_course_id_courses_id_fk": {
          "name": "community_threads_course_id_courses_id_fk",
          "tableFrom": "community_threads",
          "tableTo": "courses",
          "columnsFrom": [
            "course_id"
          ],
          "columnsTo": [
            "id"
          ],
          "onDelete": "no action",
          "onUpdate": "no action"
        },
        "community_threads_module_id_modules_id_fk": {
          "name": "community_threads_module_id_modules_id_fk",
          "tableFrom": "community_threads",
          "tableTo": "modules",
          "columnsFrom": [
            "module_id"
          ],
          "columnsTo": [
            "id"
          ],
          "onDelete": "no action",
          "onUpdate": "no action"
        }
      },
      "compositePrimaryKeys": {},
      "uniqueConstraints": {},
      "policies": {},
      "checkConstraints": {},
      "isRLSEnabled": false
    },
    "public.courses": {
      "name": "courses",
      "schema": "",
      "columns": {
        "id": {
          "name": "id",
          "type": "uuid",
          "primaryKey": true,
          "notNull": true,
          "default": "gen_random_uuid()"
        },
        "cohort_id": {
          "name": "cohort_id",
          "type": "uuid",
          "primaryKey": false,
          "notNull": true
        },
        "title": {
          "name": "title",
          "type": "text",
          "primaryKey": false,
          "notNull": true
        },
        "description": {
          "name": "description",
          "type": "text",
          "primaryKey": false,
          "notNull": true
        },
        "module_count": {
          "name": "module_count",
          "type": "integer",
          "primaryKey": false,
          "notNull": true,
          "default": 10
        },
        "icon": {
          "name": "icon",
          "type": "text",
          "primaryKey": false,
          "notNull": true,
          "default": "'📚'"
        },
        "order_index": {
          "name": "order_index",
          "type": "integer",
          "primaryKey": false,
          "notNull": true,
          "default": 0
        },
        "is_published": {
          "name": "is_published",
          "type": "boolean",
          "primaryKey": false,
          "notNull": true,
          "default": true
        },
        "created_at": {
          "name": "created_at",
          "type": "timestamp with time zone",
          "primaryKey": false,
          "notNull": true,
          "default": "now()"
        }
      },
      "indexes": {},
      "foreignKeys": {
        "courses_cohort_id_cohorts_id_fk": {
          "name": "courses_cohort_id_cohorts_id_fk",
          "tableFrom": "courses",
          "tableTo": "cohorts",
          "columnsFrom": [
            "cohort_id"
          ],
          "columnsTo": [
            "id"
          ],
          "onDelete": "no action",
          "onUpdate": "no action"
        }
      },
      "compositePrimaryKeys": {},
      "uniqueConstraints": {},
      "policies": {},
      "checkConstraints": {},
      "isRLSEnabled": false
    },
    "public.final_submissions": {
      "name": "final_submissions",
      "schema": "",
      "columns": {
        "id": {
          "name": "id",
          "type": "uuid",
          "primaryKey": true,
          "notNull": true,
          "default": "gen_random_uuid()"
        },
        "student_id": {
          "name": "student_id",
          "type": "uuid",
          "primaryKey": false,
          "notNull": true
        },
        "course_id": {
          "name": "course_id",
          "type": "uuid",
          "primaryKey": false,
          "notNull": true
        },
        "file_url": {
          "name": "file_url",
          "type": "text",
          "primaryKey": false,
          "notNull": true
        },
        "file_name": {
          "name": "file_name",
          "type": "text",
          "primaryKey": false,
          "notNull": true
        },
        "file_type": {
          "name": "file_type",
          "type": "text",
          "primaryKey": false,
          "notNull": true
        },
        "notes": {
          "name": "notes",
          "type": "text",
          "primaryKey": false,
          "notNull": false,
          "default": "''"
        },
        "submitted_at": {
          "name": "submitted_at",
          "type": "timestamp with time zone",
          "primaryKey": false,
          "notNull": true,
          "default": "now()"
        },
        "status": {
          "name": "status",
          "type": "submission_status",
          "typeSchema": "public",
          "primaryKey": false,
          "notNull": true,
          "default": "'pending'"
        },
        "score_out_of_80": {
          "name": "score_out_of_80",
          "type": "integer",
          "primaryKey": false,
          "notNull": false
        },
        "moderator_id": {
          "name": "moderator_id",
          "type": "uuid",
          "primaryKey": false,
          "notNull": false
        },
        "moderator_feedback": {
          "name": "moderator_feedback",
          "type": "text",
          "primaryKey": false,
          "notNull": false
        },
        "graded_at": {
          "name": "graded_at",
          "type": "timestamp with time zone",
          "primaryKey": false,
          "notNull": false
        }
      },
      "indexes": {},
      "foreignKeys": {
        "final_submissions_student_id_students_id_fk": {
          "name": "final_submissions_student_id_students_id_fk",
          "tableFrom": "final_submissions",
          "tableTo": "students",
          "columnsFrom": [
            "student_id"
          ],
          "columnsTo": [
            "id"
          ],
          "onDelete": "no action",
          "onUpdate": "no action"
        },
        "final_submissions_course_id_courses_id_fk": {
          "name": "final_submissions_course_id_courses_id_fk",
          "tableFrom": "final_submissions",
          "tableTo": "courses",
          "columnsFrom": [
            "course_id"
          ],
          "columnsTo": [
            "id"
          ],
          "onDelete": "no action",
          "onUpdate": "no action"
        },
        "final_submissions_moderator_id_moderators_id_fk": {
          "name": "final_submissions_moderator_id_moderators_id_fk",
          "tableFrom": "final_submissions",
          "tableTo": "moderators",
          "columnsFrom": [
            "moderator_id"
          ],
          "columnsTo": [
            "id"
          ],
          "onDelete": "no action",
          "onUpdate": "no action"
        }
      },
      "compositePrimaryKeys": {},
      "uniqueConstraints": {},
      "policies": {},
      "checkConstraints": {},
      "isRLSEnabled": false
    },
    "public.moderators": {
      "name": "moderators",
      "schema": "",
      "columns": {
        "id": {
          "name": "id",
          "type": "uuid",
          "primaryKey": true,
          "notNull": true
        },
        "full_name": {
          "name": "full_name",
          "type": "text",
          "primaryKey": false,
          "notNull": true
        },
        "email": {
          "name": "email",
          "type": "text",
          "primaryKey": false,
          "notNull": true
        },
        "created_at": {
          "name": "created_at",
          "type": "timestamp with time zone",
          "primaryKey": false,
          "notNull": true,
          "default": "now()"
        }
      },
      "indexes": {},
      "foreignKeys": {},
      "compositePrimaryKeys": {},
      "uniqueConstraints": {},
      "policies": {},
      "checkConstraints": {},
      "isRLSEnabled": false
    },
    "public.module_progress": {
      "name": "module_progress",
      "schema": "",
      "columns": {
        "id": {
          "name": "id",
          "type": "uuid",
          "primaryKey": true,
          "notNull": true,
          "default": "gen_random_uuid()"
        },
        "student_id": {
          "name": "student_id",
          "type": "uuid",
          "primaryKey": false,
          "notNull": true
        },
        "module_id": {
          "name": "module_id",
          "type": "uuid",
          "primaryKey": false,
          "notNull": true
        },
        "lesson_viewed_at": {
          "name": "lesson_viewed_at",
          "type": "timestamp with time zone",
          "primaryKey": false,
          "notNull": false
        },
        "quiz_passed_at": {
          "name": "quiz_passed_at",
          "type": "timestamp with time zone",
          "primaryKey": false,
          "notNull": false
        },
        "best_quiz_score": {
          "name": "best_quiz_score",
          "type": "integer",
          "primaryKey": false,
          "notNull": false
        },
        "completed_at": {
          "name": "completed_at",
          "type": "timestamp with time zone",
          "primaryKey": false,
          "notNull": false
        }
      },
      "indexes": {
        "module_progress_student_idx": {
          "name": "module_progress_student_idx",
          "columns": [
            {
              "expression": "student_id",
              "isExpression": false,
              "asc": true,
              "nulls": "last"
            }
          ],
          "isUnique": false,
          "concurrently": false,
          "method": "btree",
          "with": {}
        }
      },
      "foreignKeys": {
        "module_progress_student_id_students_id_fk": {
          "name": "module_progress_student_id_students_id_fk",
          "tableFrom": "module_progress",
          "tableTo": "students",
          "columnsFrom": [
            "student_id"
          ],
          "columnsTo": [
            "id"
          ],
          "onDelete": "no action",
          "onUpdate": "no action"
        },
        "module_progress_module_id_modules_id_fk": {
          "name": "module_progress_module_id_modules_id_fk",
          "tableFrom": "module_progress",
          "tableTo": "modules",
          "columnsFrom": [
            "module_id"
          ],
          "columnsTo": [
            "id"
          ],
          "onDelete": "no action",
          "onUpdate": "no action"
        }
      },
      "compositePrimaryKeys": {},
      "uniqueConstraints": {
        "module_progress_student_module_uniq": {
          "name": "module_progress_student_module_uniq",
          "nullsNotDistinct": false,
          "columns": [
            "student_id",
            "module_id"
          ]
        }
      },
      "policies": {},
      "checkConstraints": {},
      "isRLSEnabled": false
    },
    "public.modules": {
      "name": "modules",
      "schema": "",
      "columns": {
        "id": {
          "name": "id",
          "type": "uuid",
          "primaryKey": true,
          "notNull": true,
          "default": "gen_random_uuid()"
        },
        "course_id": {
          "name": "course_id",
          "type": "uuid",
          "primaryKey": false,
          "notNull": true
        },
        "title": {
          "name": "title",
          "type": "text",
          "primaryKey": false,
          "notNull": true
        },
        "objective": {
          "name": "objective",
          "type": "text",
          "primaryKey": false,
          "notNull": true
        },
        "content_blocks": {
          "name": "content_blocks",
          "type": "jsonb",
          "primaryKey": false,
          "notNull": true
        },
        "order_index": {
          "name": "order_index",
          "type": "integer",
          "primaryKey": false,
          "notNull": true
        },
        "created_at": {
          "name": "created_at",
          "type": "timestamp with time zone",
          "primaryKey": false,
          "notNull": true,
          "default": "now()"
        }
      },
      "indexes": {},
      "foreignKeys": {
        "modules_course_id_courses_id_fk": {
          "name": "modules_course_id_courses_id_fk",
          "tableFrom": "modules",
          "tableTo": "courses",
          "columnsFrom": [
            "course_id"
          ],
          "columnsTo": [
            "id"
          ],
          "onDelete": "no action",
          "onUpdate": "no action"
        }
      },
      "compositePrimaryKeys": {},
      "uniqueConstraints": {},
      "policies": {},
      "checkConstraints": {},
      "isRLSEnabled": false
    },
    "public.notifications": {
      "name": "notifications",
      "schema": "",
      "columns": {
        "id": {
          "name": "id",
          "type": "uuid",
          "primaryKey": true,
          "notNull": true,
          "default": "gen_random_uuid()"
        },
        "user_id": {
          "name": "user_id",
          "type": "uuid",
          "primaryKey": false,
          "notNull": true
        },
        "type": {
          "name": "type",
          "type": "text",
          "primaryKey": false,
          "notNull": true
        },
        "title": {
          "name": "title",
          "type": "text",
          "primaryKey": false,
          "notNull": true
        },
        "body": {
          "name": "body",
          "type": "text",
          "primaryKey": false,
          "notNull": true
        },
        "data": {
          "name": "data",
          "type": "text",
          "primaryKey": false,
          "notNull": false
        },
        "is_read": {
          "name": "is_read",
          "type": "boolean",
          "primaryKey": false,
          "notNull": true,
          "default": false
        },
        "created_at": {
          "name": "created_at",
          "type": "timestamp with time zone",
          "primaryKey": false,
          "notNull": true,
          "default": "now()"
        }
      },
      "indexes": {
        "notifications_user_idx": {
          "name": "notifications_user_idx",
          "columns": [
            {
              "expression": "user_id",
              "isExpression": false,
              "asc": true,
              "nulls": "last"
            }
          ],
          "isUnique": false,
          "concurrently": false,
          "method": "btree",
          "with": {}
        },
        "notifications_unread_idx": {
          "name": "notifications_unread_idx",
          "columns": [
            {
              "expression": "user_id",
              "isExpression": false,
              "asc": true,
              "nulls": "last"
            },
            {
              "expression": "is_read",
              "isExpression": false,
              "asc": true,
              "nulls": "last"
            }
          ],
          "isUnique": false,
          "concurrently": false,
          "method": "btree",
          "with": {}
        }
      },
      "foreignKeys": {},
      "compositePrimaryKeys": {},
      "uniqueConstraints": {},
      "policies": {},
      "checkConstraints": {},
      "isRLSEnabled": false
    },
    "public.quiz_attempts": {
      "name": "quiz_attempts",
      "schema": "",
      "columns": {
        "id": {
          "name": "id",
          "type": "uuid",
          "primaryKey": true,
          "notNull": true,
          "default": "gen_random_uuid()"
        },
        "student_id": {
          "name": "student_id",
          "type": "uuid",
          "primaryKey": false,
          "notNull": true
        },
        "module_id": {
          "name": "module_id",
          "type": "uuid",
          "primaryKey": false,
          "notNull": true
        },
        "score_out_of_20": {
          "name": "score_out_of_20",
          "type": "integer",
          "primaryKey": false,
          "notNull": true
        },
        "answers": {
          "name": "answers",
          "type": "jsonb",
          "primaryKey": false,
          "notNull": true
        },
        "attempted_at": {
          "name": "attempted_at",
          "type": "timestamp with time zone",
          "primaryKey": false,
          "notNull": true,
          "default": "now()"
        }
      },
      "indexes": {
        "quiz_attempts_student_module_idx": {
          "name": "quiz_attempts_student_module_idx",
          "columns": [
            {
              "expression": "student_id",
              "isExpression": false,
              "asc": true,
              "nulls": "last"
            },
            {
              "expression": "module_id",
              "isExpression": false,
              "asc": true,
              "nulls": "last"
            }
          ],
          "isUnique": false,
          "concurrently": false,
          "method": "btree",
          "with": {}
        }
      },
      "foreignKeys": {
        "quiz_attempts_student_id_students_id_fk": {
          "name": "quiz_attempts_student_id_students_id_fk",
          "tableFrom": "quiz_attempts",
          "tableTo": "students",
          "columnsFrom": [
            "student_id"
          ],
          "columnsTo": [
            "id"
          ],
          "onDelete": "no action",
          "onUpdate": "no action"
        },
        "quiz_attempts_module_id_modules_id_fk": {
          "name": "quiz_attempts_module_id_modules_id_fk",
          "tableFrom": "quiz_attempts",
          "tableTo": "modules",
          "columnsFrom": [
            "module_id"
          ],
          "columnsTo": [
            "id"
          ],
          "onDelete": "no action",
          "onUpdate": "no action"
        }
      },
      "compositePrimaryKeys": {},
      "uniqueConstraints": {},
      "policies": {},
      "checkConstraints": {},
      "isRLSEnabled": false
    },
    "public.quiz_questions": {
      "name": "quiz_questions",
      "schema": "",
      "columns": {
        "id": {
          "name": "id",
          "type": "uuid",
          "primaryKey": true,
          "notNull": true,
          "default": "gen_random_uuid()"
        },
        "module_id": {
          "name": "module_id",
          "type": "uuid",
          "primaryKey": false,
          "notNull": true
        },
        "question": {
          "name": "question",
          "type": "text",
          "primaryKey": false,
          "notNull": true
        },
        "options": {
          "name": "options",
          "type": "jsonb",
          "primaryKey": false,
          "notNull": true
        },
        "correct_index": {
          "name": "correct_index",
          "type": "integer",
          "primaryKey": false,
          "notNull": true
        },
        "order_index": {
          "name": "order_index",
          "type": "integer",
          "primaryKey": false,
          "notNull": true
        },
        "created_at": {
          "name": "created_at",
          "type": "timestamp with time zone",
          "primaryKey": false,
          "notNull": true,
          "default": "now()"
        }
      },
      "indexes": {},
      "foreignKeys": {
        "quiz_questions_module_id_modules_id_fk": {
          "name": "quiz_questions_module_id_modules_id_fk",
          "tableFrom": "quiz_questions",
          "tableTo": "modules",
          "columnsFrom": [
            "module_id"
          ],
          "columnsTo": [
            "id"
          ],
          "onDelete": "no action",
          "onUpdate": "no action"
        }
      },
      "compositePrimaryKeys": {},
      "uniqueConstraints": {},
      "policies": {},
      "checkConstraints": {},
      "isRLSEnabled": false
    },
    "public.schools": {
      "name": "schools",
      "schema": "",
      "columns": {
        "id": {
          "name": "id",
          "type": "uuid",
          "primaryKey": true,
          "notNull": true,
          "default": "gen_random_uuid()"
        },
        "name": {
          "name": "name",
          "type": "text",
          "primaryKey": false,
          "notNull": true
        },
        "registration_code": {
          "name": "registration_code",
          "type": "text",
          "primaryKey": false,
          "notNull": true
        },
        "is_active": {
          "name": "is_active",
          "type": "boolean",
          "primaryKey": false,
          "notNull": true,
          "default": true
        },
        "created_at": {
          "name": "created_at",
          "type": "timestamp with time zone",
          "primaryKey": false,
          "notNull": true,
          "default": "now()"
        }
      },
      "indexes": {
        "schools_registration_code_idx": {
          "name": "schools_registration_code_idx",
          "columns": [
            {
              "expression": "registration_code",
              "isExpression": false,
              "asc": true,
              "nulls": "last"
            }
          ],
          "isUnique": true,
          "concurrently": false,
          "method": "btree",
          "with": {}
        }
      },
      "foreignKeys": {},
      "compositePrimaryKeys": {},
      "uniqueConstraints": {},
      "policies": {},
      "checkConstraints": {},
      "isRLSEnabled": false
    },
    "public.students": {
      "name": "students",
      "schema": "",
      "columns": {
        "id": {
          "name": "id",
          "type": "uuid",
          "primaryKey": true,
          "notNull": true
        },
        "full_name": {
          "name": "full_name",
          "type": "text",
          "primaryKey": false,
          "notNull": true
        },
        "email": {
          "name": "email",
          "type": "text",
          "primaryKey": false,
          "notNull": true
        },
        "grade": {
          "name": "grade",
          "type": "integer",
          "primaryKey": false,
          "notNull": true
        },
        "school_id": {
          "name": "school_id",
          "type": "uuid",
          "primaryKey": false,
          "notNull": true
        },
        "cohort_id": {
          "name": "cohort_id",
          "type": "uuid",
          "primaryKey": false,
          "notNull": true
        },
        "guardian_contact": {
          "name": "guardian_contact",
          "type": "text",
          "primaryKey": false,
          "notNull": false
        },
        "joined_at": {
          "name": "joined_at",
          "type": "timestamp with time zone",
          "primaryKey": false,
          "notNull": true,
          "default": "now()"
        }
      },
      "indexes": {},
      "foreignKeys": {
        "students_school_id_schools_id_fk": {
          "name": "students_school_id_schools_id_fk",
          "tableFrom": "students",
          "tableTo": "schools",
          "columnsFrom": [
            "school_id"
          ],
          "columnsTo": [
            "id"
          ],
          "onDelete": "no action",
          "onUpdate": "no action"
        },
        "students_cohort_id_cohorts_id_fk": {
          "name": "students_cohort_id_cohorts_id_fk",
          "tableFrom": "students",
          "tableTo": "cohorts",
          "columnsFrom": [
            "cohort_id"
          ],
          "columnsTo": [
            "id"
          ],
          "onDelete": "no action",
          "onUpdate": "no action"
        }
      },
      "compositePrimaryKeys": {},
      "uniqueConstraints": {},
      "policies": {},
      "checkConstraints": {},
      "isRLSEnabled": false
    }
  },
  "enums": {
    "public.course_progress_status": {
      "name": "course_progress_status",
      "schema": "public",
      "values": [
        "not_started",
        "in_progress",
        "modules_done",
        "completed"
      ]
    },
    "public.submission_status": {
      "name": "submission_status",
      "schema": "public",
      "values": [
        "pending",
        "graded"
      ]
    },
    "public.user_role": {
      "name": "user_role",
      "schema": "public",
      "values": [
        "student",
        "moderator"
      ]
    }
  },
  "schemas": {},
  "sequences": {},
  "roles": {},
  "policies": {},
  "views": {},
  "_meta": {
    "columns": {},
    "schemas": {},
    "tables": {}
  }
}